torchdefenses/__init__.py
torchdefenses/nn/__init__.py
torchdefenses/nn/functional.py
torchdefenses/nn/robmodel.py
torchdefenses/nn/modules/__init__.py
torchdefenses/nn/modules/normalize.py
torchdefenses/trainer/__init__.py
torchdefenses/trainer/_rm.py
torchdefenses/trainer/_trainer.py
torchdefenses/trainer/_vis.py
torchdefenses/trainer/advtrainer.py
torchdefenses/trainer/standard.py
torchdefenses/trainer/certified_defenses/__init__.py
torchdefenses/trainer/empirical_defenses/__init__.py
torchdefenses/trainer/empirical_defenses/at.py
torchdefenses/trainer/empirical_defenses/atrades.py
torchdefenses/trainer/empirical_defenses/bat.py
torchdefenses/trainer/empirical_defenses/fast.py
torchdefenses/trainer/empirical_defenses/free.py
torchdefenses/trainer/empirical_defenses/gradalign.py
torchdefenses/trainer/empirical_defenses/mart.py
torchdefenses/trainer/empirical_defenses/trades.py
torchdefenses/utils/__init__.py
torchdefenses/utils/cuda.py
torchdefenses/utils/datasets/__init__.py
torchdefenses/utils/datasets/base.py
torchdefenses/utils/datasets/cifar_corrupt.py
torchdefenses/utils/datasets/cifar_unsup.py
torchdefenses/utils/datasets/mnistm.py
torchdefenses/utils/datasets/tinyimagenet.py
torchdefenses/utils/models/__init__.py
torchdefenses/utils/models/densenet.py
torchdefenses/utils/models/lenet.py
torchdefenses/utils/models/mnist_ates.py
torchdefenses/utils/models/mnist_dat.py
torchdefenses/utils/models/mnist_fast.py
torchdefenses/utils/models/preactresnet.py
torchdefenses/utils/models/resnet.py
torchdefenses/utils/models/vgg.py
torchdefenses/utils/models/wideresnet.py
torchdefenses-0.1.25.dist-info/LICENSE
torchdefenses-0.1.25.dist-info/METADATA
torchdefenses-0.1.25.dist-info/WHEEL
torchdefenses-0.1.25.dist-info/top_level.txt
torchdefenses-0.1.25.dist-info/RECORD
